{"dates":[{"date":"Sep 24, 2020","hasGoal":false,"hasRevenue":false,"sessionCount":1,"sessions":[{"duration":"00:29","deviceCategory":"desktop","channel":"Direct","activitySummary":{"EVENT":"1","PAGEVIEW":"1"},"activities":[{"time":"7:37 AM","type":"EVENT","repeatActivityTimes":[],"details":[{"Event category":["30 sec Engagement"],"Event action":["time on page more than 30 seconds"],"Event label":["(not set)"],"Event count":["1"],"Event value":["0"]}],"name":"time on page more than 30 seconds","on":"30 sec Engagement"},{"time":"7:36 AM","type":"PAGEVIEW","repeatActivityTimes":[],"details":[{"Page title":["Group chat - The Mix"],"Page URL":["/get-support/group-chat"]}],"pageTitle":"Group chat - The Mix"}]}]},{"date":"Sep 16, 2020","hasGoal":false,"hasRevenue":false,"sessionCount":1,"sessions":[{"duration":"00:30","deviceCategory":"desktop","channel":"Direct","activitySummary":{"EVENT":"1","PAGEVIEW":"1"},"activities":[{"time":"12:13 PM","type":"EVENT","repeatActivityTimes":[],"details":[{"Event category":["30 sec Engagement"],"Event action":["time on page more than 30 seconds"],"Event label":["(not set)"],"Event count":["1"],"Event value":["0"]}],"name":"time on page more than 30 seconds","on":"30 sec Engagement"},{"time":"12:12 PM","type":"PAGEVIEW","repeatActivityTimes":[],"details":[{"Page title":["Organisation details - The Mix"],"Page URL":["/get-support/find-local-services/west-london-centre-for-counselling-5964.html"]}],"pageTitle":"Organisation details - The Mix"}]}]},{"date":"Sep 11, 2020","hasGoal":false,"hasRevenue":false,"sessionCount":1,"sessions":[{"duration":"00:00","deviceCategory":"desktop","channel":"Direct","activitySummary":{"PAGEVIEW":"1"},"activities":[{"time":"2:09 PM","type":"PAGEVIEW","repeatActivityTimes":[],"details":[{"Page title":["The Mix - Essential support for under 25s"],"Page URL":["/"]}],"pageTitle":"The Mix - Essential support for under 25s"}]}]},{"date":"Sep 10, 2020","hasGoal":false,"hasRevenue":false,"sessionCount":1,"sessions":[{"duration":"00:29","deviceCategory":"desktop","channel":"Direct","activitySummary":{"EVENT":"1","PAGEVIEW":"1"},"activities":[{"time":"5:49 PM","type":"EVENT","repeatActivityTimes":[],"details":[{"Event category":["30 sec Engagement"],"Event action":["time on page more than 30 seconds"],"Event label":["(not set)"],"Event count":["1"],"Event value":["0"]}],"name":"time on page more than 30 seconds","on":"30 sec Engagement"},{"time":"5:49 PM","type":"PAGEVIEW","repeatActivityTimes":[],"details":[{"Page title":["Find local services - The Mix"],"Page URL":["/get-support/find-local-services"]}],"pageTitle":"Find local services - The Mix"}]}]},{"date":"Sep 8, 2020","hasGoal":false,"hasRevenue":false,"sessionCount":1,"sessions":[{"duration":"00:34","deviceCategory":"mobile","channel":"Direct","activitySummary":{"EVENT":"1","PAGEVIEW":"2"},"activities":[{"time":"8:18 AM","type":"EVENT","repeatActivityTimes":[],"details":[{"Event category":["30 sec Engagement"],"Event action":["time on page more than 30 seconds"],"Event label":["(not set)"],"Event count":["1"],"Event value":["0"]}],"name":"time on page more than 30 seconds","on":"30 sec Engagement"},{"time":"8:17 AM","type":"PAGEVIEW","repeatActivityTimes":[],"details":[{"Page title":["Speak to Our Team - The Mix"],"Page URL":["/get-support/speak-to-our-team"]}],"pageTitle":"Speak to Our Team - The Mix"},{"time":"8:17 AM","type":"PAGEVIEW","repeatActivityTimes":[],"details":[{"Page title":["The Mix - Essential support for under 25s"],"Page URL":["/"]}],"pageTitle":"The Mix - Essential support for under 25s"}]}]},{"date":"Sep 7, 2020","hasGoal":false,"hasRevenue":false,"sessionCount":3,"sessions":[{"duration":"00:29","deviceCategory":"desktop","channel":"Direct","activitySummary":{"EVENT":"1","PAGEVIEW":"1"},"activities":[{"time":"11:48 AM","type":"EVENT","repeatActivityTimes":[],"details":[{"Event category":["30 sec Engagement"],"Event action":["time on page more than 30 seconds"],"Event label":["(not set)"],"Event count":["1"],"Event value":["0"]}],"name":"time on page more than 30 seconds","on":"30 sec Engagement"},{"time":"11:47 AM","type":"PAGEVIEW","repeatActivityTimes":[],"details":[{"Page title":["Find local services - The Mix"],"Page URL":["/get-support/find-local-services"]}],"pageTitle":"Find local services - The Mix"}]},{"duration":"00:29","deviceCategory":"desktop","channel":"Direct","activitySummary":{"EVENT":"1","PAGEVIEW":"1"},"activities":[{"time":"10:59 AM","type":"EVENT","repeatActivityTimes":[],"details":[{"Event category":["30 sec Engagement"],"Event action":["time on page more than 30 seconds"],"Event label":["(not set)"],"Event count":["1"],"Event value":["0"]}],"name":"time on page more than 30 seconds","on":"30 sec Engagement"},{"time":"10:59 AM","type":"PAGEVIEW","repeatActivityTimes":[],"details":[{"Page title":["Find local services - The Mix"],"Page URL":["/get-support/find-local-services"]}],"pageTitle":"Find local services - The Mix"}]},{"duration":"00:33","deviceCategory":"desktop","channel":"Direct","activitySummary":{"EVENT":"1","PAGEVIEW":"2"},"activities":[{"time":"9:55 AM","type":"EVENT","repeatActivityTimes":[],"details":[{"Event category":["30 sec Engagement"],"Event action":["time on page more than 30 seconds"],"Event label":["(not set)"],"Event count":["1"],"Event value":["0"]}],"name":"time on page more than 30 seconds","on":"30 sec Engagement"},{"time":"9:55 AM","type":"PAGEVIEW","repeatActivityTimes":[],"details":[{"Page title":["Find local services - The Mix"],"Page URL":["/get-support/find-local-services"]}],"pageTitle":"Find local services - The Mix"},{"time":"9:55 AM","type":"PAGEVIEW","repeatActivityTimes":[],"details":[{"Page title":["The Mix - Essential support for under 25s"],"Page URL":["/"]}],"pageTitle":"The Mix - Essential support for under 25s"}]}]},{"date":"Sep 4, 2020","hasGoal":false,"hasRevenue":false,"sessionCount":1,"sessions":[{"duration":"00:00","deviceCategory":"desktop","channel":"Direct","activitySummary":{"PAGEVIEW":"1"},"activities":[{"time":"8:20 AM","type":"PAGEVIEW","repeatActivityTimes":[],"details":[{"Page title":["The Mix - Essential support for under 25s"],"Page URL":["/"]}],"pageTitle":"The Mix - Essential support for under 25s"}]}]},{"date":"Sep 3, 2020","hasGoal":false,"hasRevenue":false,"sessionCount":6,"sessions":[{"duration":"00:29","deviceCategory":"desktop","channel":"Direct","activitySummary":{"EVENT":"1","PAGEVIEW":"1"},"activities":[{"time":"1:47 PM","type":"EVENT","repeatActivityTimes":[],"details":[{"Event category":["30 sec Engagement"],"Event action":["time on page more than 30 seconds"],"Event label":["(not set)"],"Event count":["1"],"Event value":["0"]}],"name":"time on page more than 30 seconds","on":"30 sec Engagement"},{"time":"1:46 PM","type":"PAGEVIEW","repeatActivityTimes":[],"details":[{"Page title":["The Mix - Essential support for under 25s"],"Page URL":["/"]}],"pageTitle":"The Mix - Essential support for under 25s"}]},{"duration":"00:00","deviceCategory":"desktop","channel":"Direct","activitySummary":{"PAGEVIEW":"1"},"activities":[{"time":"1:36 PM","type":"PAGEVIEW","repeatActivityTimes":[],"details":[{"Page title":["The Mix - Essential support for under 25s"],"Page URL":["/"]}],"pageTitle":"The Mix - Essential support for under 25s"}]},{"duration":"55:16","deviceCategory":"desktop","channel":"Direct","activitySummary":{"EVENT":"7","PAGEVIEW":"20"},"activities":[{"time":"12:52 PM","type":"PAGEVIEW","repeatActivityTimes":[],"details":[{"Page title":["The Mix - Essential support for under 25s"],"Page URL":["/"]}],"pageTitle":"The Mix - Essential support for under 25s"},{"time":"12:52 PM","type":"PAGEVIEW","repeatActivityTimes":[],"details":[{"Page title":["Drink & Drugs - The Mix"],"Page URL":["/drink-and-drugs"]}],"pageTitle":"Drink & Drugs - The Mix"},{"time":"12:52 PM","type":"PAGEVIEW","repeatActivityTimes":[],"details":[{"Page title":["Planning for the future: How to manage your money - The Mix"],"Page URL":["/money/money-management-tips/planning-what-to-do-with-my-money-37400.html"]}],"pageTitle":"Planning for the future: How to manage your money - The Mix"},{"time":"12:52 PM","type":"PAGEVIEW","repeatActivityTimes":[],"details":[{"Page title":["The Mix - Essential support for under 25s"],"Page URL":["/"]}],"pageTitle":"The Mix - Essential support for under 25s"},{"time":"12:52 PM","type":"PAGEVIEW","repeatActivityTimes":[],"details":[{"Page title":["Ambassador voices: Coming out, on extra hard mode - The Mix"],"Page URL":["/sex-and-relationships/gender-and-sexuality/young-ambassador-voices-coming-out-on-extra-hard-mode-36607.html"]}],"pageTitle":"Ambassador voices: Coming out, on extra hard mode - The Mix"},{"time":"12:52 PM","type":"PAGEVIEW","repeatActivityTimes":[],"details":[{"Page title":["Sex & Relationships - The Mix"],"Page URL":["/sex-and-relationships"]}],"pageTitle":"Sex & Relationships - The Mix"},{"time":"12:52 PM","type":"PAGEVIEW","repeatActivityTimes":[],"details":[{"Page title":["The Mix - Essential support for under 25s"],"Page URL":["/"]}],"pageTitle":"The Mix - Essential support for under 25s"},{"time":"12:52 PM","type":"PAGEVIEW","repeatActivityTimes":[],"details":[{"Page title":["The Mix - Essential support for under 25s"],"Page URL":["/"]}],"pageTitle":"The Mix - Essential support for under 25s"},{"time":"12:51 PM","type":"PAGEVIEW","repeatActivityTimes":[],"details":[{"Page title":["The Mix - Essential support for under 25s"],"Page URL":["/"]}],"pageTitle":"The Mix - Essential support for under 25s"},{"time":"12:35 PM","type":"EVENT","repeatActivityTimes":[],"details":[{"Event category":["30 sec Engagement"],"Event action":["time on page more than 30 seconds"],"Event label":["(not set)"],"Event count":["1"],"Event value":["0"]}],"name":"time on page more than 30 seconds","on":"30 sec Engagement"},{"time":"12:35 PM","type":"PAGEVIEW","repeatActivityTimes":[],"details":[{"Page title":["The Mix - Essential support for under 25s"],"Page URL":["/"]}],"pageTitle":"The Mix - Essential support for under 25s"},{"time":"12:28 PM","type":"EVENT","repeatActivityTimes":[],"details":[{"Event category":["30 sec Engagement"],"Event action":["time on page more than 30 seconds"],"Event label":["(not set)"],"Event count":["1"],"Event value":["0"]}],"name":"time on page more than 30 seconds","on":"30 sec Engagement"},{"time":"12:28 PM","type":"PAGEVIEW","repeatActivityTimes":[],"details":[{"Page title":["The Mix - Essential support for under 25s"],"Page URL":["/"]}],"pageTitle":"The Mix - Essential support for under 25s"},{"time":"12:25 PM","type":"EVENT","repeatActivityTimes":[],"details":[{"Event category":["30 sec Engagement"],"Event action":["time on page more than 30 seconds"],"Event label":["(not set)"],"Event count":["1"],"Event value":["0"]}],"name":"time on page more than 30 seconds","on":"30 sec Engagement"},{"time":"12:24 PM","type":"PAGEVIEW","repeatActivityTimes":[],"details":[{"Page title":["The Mix - Essential support for under 25s"],"Page URL":["/"]}],"pageTitle":"The Mix - Essential support for under 25s"},{"time":"12:18 PM","type":"EVENT","repeatActivityTimes":[],"details":[{"Event category":["30 sec Engagement"],"Event action":["time on page more than 30 seconds"],"Event label":["(not set)"],"Event count":["1"],"Event value":["0"]}],"name":"time on page more than 30 seconds","on":"30 sec Engagement"},{"time":"12:17 PM","type":"PAGEVIEW","repeatActivityTimes":[],"details":[{"Page title":["The Mix - Essential support for under 25s"],"Page URL":["/"]}],"pageTitle":"The Mix - Essential support for under 25s"},{"time":"12:17 PM","type":"EVENT","repeatActivityTimes":[],"details":[{"Event category":["30 sec Engagement"],"Event action":["time on page more than 30 seconds"],"Event label":["(not set)"],"Event count":["1"],"Event value":["0"]}],"name":"time on page more than 30 seconds","on":"30 sec Engagement"},{"time":"12:16 PM","type":"PAGEVIEW","repeatActivityTimes":[],"details":[{"Page title":["The Mix - Essential support for under 25s"],"Page URL":["/"]}],"pageTitle":"The Mix - Essential support for under 25s"},{"time":"12:16 PM","type":"PAGEVIEW","repeatActivityTimes":[],"details":[{"Page title":["Your Body - The Mix"],"Page URL":["/your-body"]}],"pageTitle":"Your Body - The Mix"},{"time":"12:16 PM","type":"PAGEVIEW","repeatActivityTimes":[],"details":[{"Page title":["Sex & Relationships - The Mix"],"Page URL":["/sex-and-relationships"]}],"pageTitle":"Sex & Relationships - The Mix"},{"time":"12:16 PM","type":"PAGEVIEW","repeatActivityTimes":[],"details":[{"Page title":["The Mix - Essential support for under 25s"],"Page URL":["/"]}],"pageTitle":"The Mix - Essential support for under 25s"},{"time":"12:00 PM","type":"PAGEVIEW","repeatActivityTimes":[],"details":[{"Page title":["The Mix - Essential support for under 25s"],"Page URL":["/"]}],"pageTitle":"The Mix - Essential support for under 25s"},{"time":"11:58 AM","type":"EVENT","repeatActivityTimes":[],"details":[{"Event category":["30 sec Engagement"],"Event action":["time on page more than 30 seconds"],"Event label":["(not set)"],"Event count":["1"],"Event value":["0"]}],"name":"time on page more than 30 seconds","on":"30 sec Engagement"},{"time":"11:58 AM","type":"PAGEVIEW","repeatActivityTimes":[],"details":[{"Page title":["The Mix - Essential support for under 25s"],"Page URL":["/"]}],"pageTitle":"The Mix - Essential support for under 25s"},{"time":"11:58 AM","type":"EVENT","repeatActivityTimes":[],"details":[{"Event category":["30 sec Engagement"],"Event action":["time on page more than 30 seconds"],"Event label":["(not set)"],"Event count":["1"],"Event value":["0"]}],"name":"time on page more than 30 seconds","on":"30 sec Engagement"},{"time":"11:57 AM","type":"PAGEVIEW","repeatActivityTimes":[],"details":[{"Page title":["The Mix - Essential support for under 25s"],"Page URL":["/"]}],"pageTitle":"The Mix - Essential support for under 25s"}]},{"duration":"07:43","deviceCategory":"desktop","channel":"Direct","activitySummary":{"EVENT":"2","PAGEVIEW":"3"},"activities":[{"time":"12:04 PM","type":"EVENT","repeatActivityTimes":[],"details":[{"Event category":["30 sec Engagement"],"Event action":["time on page more than 30 seconds"],"Event label":["(not set)"],"Event count":["1"],"Event value":["0"]}],"name":"time on page more than 30 seconds","on":"30 sec Engagement"},{"time":"12:03 PM","type":"PAGEVIEW","repeatActivityTimes":[],"details":[{"Page title":["The Mix - Essential support for under 25s"],"Page URL":["/"]}],"pageTitle":"The Mix - Essential support for under 25s"},{"time":"11:57 AM","type":"EVENT","repeatActivityTimes":[],"details":[{"Event category":["30 sec Engagement"],"Event action":["time on page more than 30 seconds"],"Event label":["(not set)"],"Event count":["1"],"Event value":["0"]}],"name":"time on page more than 30 seconds","on":"30 sec Engagement"},{"time":"11:57 AM","type":"PAGEVIEW","repeatActivityTimes":[],"details":[{"Page title":["The Mix - Essential support for under 25s"],"Page URL":["/"]}],"pageTitle":"The Mix - Essential support for under 25s"},{"time":"11:56 AM","type":"PAGEVIEW","repeatActivityTimes":[],"details":[{"Page title":["The Mix - Essential support for under 25s"],"Page URL":["/"]}],"pageTitle":"The Mix - Essential support for under 25s"}]},{"duration":"25:22","deviceCategory":"desktop","channel":"Direct","activitySummary":{"EVENT":"1","PAGEVIEW":"2"},"activities":[{"time":"10:37 AM","type":"EVENT","repeatActivityTimes":[],"details":[{"Event category":["30 sec Engagement"],"Event action":["time on page more than 30 seconds"],"Event label":["(not set)"],"Event count":["1"],"Event value":["0"]}],"name":"time on page more than 30 seconds","on":"30 sec Engagement"},{"time":"10:37 AM","type":"PAGEVIEW","repeatActivityTimes":[],"details":[{"Page title":["The Mix - Essential support for under 25s"],"Page URL":["/"]}],"pageTitle":"The Mix - Essential support for under 25s"},{"time":"10:12 AM","type":"PAGEVIEW","repeatActivityTimes":[],"details":[{"Page title":["Courses - The Mix"],"Page URL":["/get-involved/skill-up"]}],"pageTitle":"Courses - The Mix"}]},{"duration":"00:28","deviceCategory":"desktop","channel":"Direct","activitySummary":{"EVENT":"1","PAGEVIEW":"1"},"activities":[{"time":"8:35 AM","type":"EVENT","repeatActivityTimes":[],"details":[{"Event category":["30 sec Engagement"],"Event action":["time on page more than 30 seconds"],"Event label":["(not set)"],"Event count":["1"],"Event value":["0"]}],"name":"time on page more than 30 seconds","on":"30 sec Engagement"},{"time":"8:35 AM","type":"PAGEVIEW","repeatActivityTimes":[],"details":[{"Page title":["The Mix - Essential support for under 25s"],"Page URL":["/"]}],"pageTitle":"The Mix - Essential support for under 25s"}]}]},{"date":"Sep 2, 2020","hasGoal":false,"hasRevenue":false,"sessionCount":1,"sessions":[{"duration":"00:30","deviceCategory":"desktop","channel":"Direct","activitySummary":{"EVENT":"1","PAGEVIEW":"1"},"activities":[{"time":"9:17 AM","type":"EVENT","repeatActivityTimes":[],"details":[{"Event category":["30 sec Engagement"],"Event action":["time on page more than 30 seconds"],"Event label":["(not set)"],"Event count":["1"],"Event value":["0"]}],"name":"time on page more than 30 seconds","on":"30 sec Engagement"},{"time":"9:17 AM","type":"PAGEVIEW","repeatActivityTimes":[],"details":[{"Page title":["The Mix - Essential support for under 25s"],"Page URL":["/"]}],"pageTitle":"The Mix - Essential support for under 25s"}]}]},{"date":"Sep 1, 2020","hasGoal":false,"hasRevenue":false,"sessionCount":4,"sessions":[{"duration":"11:47","deviceCategory":"desktop","channel":"Direct","activitySummary":{"EVENT":"5","PAGEVIEW":"9"},"activities":[{"time":"3:22 PM","type":"EVENT","repeatActivityTimes":[],"details":[{"Event category":["30 sec Engagement"],"Event action":["time on page more than 30 seconds"],"Event label":["(not set)"],"Event count":["1"],"Event value":["0"]}],"name":"time on page more than 30 seconds","on":"30 sec Engagement"},{"time":"3:21 PM","type":"EVENT","repeatActivityTimes":[],"details":[{"Event category":["30 sec Engagement"],"Event action":["time on page more than 30 seconds"],"Event label":["(not set)"],"Event count":["1"],"Event value":["0"]}],"name":"time on page more than 30 seconds","on":"30 sec Engagement"},{"time":"3:21 PM","type":"PAGEVIEW","repeatActivityTimes":[],"details":[{"Page title":["Gender & Sexuality - The Mix"],"Page URL":["/sex-and-relationships/gender-and-sexuality"]}],"pageTitle":"Gender & Sexuality - The Mix"},{"time":"3:21 PM","type":"PAGEVIEW","repeatActivityTimes":[],"details":[{"Page title":["Sex & Relationships - The Mix"],"Page URL":["/sex-and-relationships"]}],"pageTitle":"Sex & Relationships - The Mix"},{"time":"3:21 PM","type":"PAGEVIEW","repeatActivityTimes":[],"details":[{"Page title":["The Mix - Essential support for under 25s"],"Page URL":["/"]}],"pageTitle":"The Mix - Essential support for under 25s"},{"time":"3:21 PM","type":"PAGEVIEW","repeatActivityTimes":[],"details":[{"Page title":["Exploring your sexuality? Switchboard LGBT+ Helpline offer their expert advice - The Mix"],"Page URL":["/sex-and-relationships/gender-and-sexuality/are-you-exploring-your-sexuality-switchboard-lgbt-helpline-offer-their-expert-advice-35438.html"]}],"pageTitle":"Exploring your sexuality? Switchboard LGBT+ Helpline offer their expert advice - The Mix"},{"time":"3:20 PM","type":"EVENT","repeatActivityTimes":[],"details":[{"Event category":["30 sec Engagement"],"Event action":["time on page more than 30 seconds"],"Event label":["(not set)"],"Event count":["1"],"Event value":["0"]}],"name":"time on page more than 30 seconds","on":"30 sec Engagement"},{"time":"3:20 PM","type":"PAGEVIEW","repeatActivityTimes":[],"details":[{"Page title":["Exploring your sexuality? Switchboard LGBT+ Helpline offer their expert advice - The Mix"],"Page URL":["/sex-and-relationships/gender-and-sexuality/are-you-exploring-your-sexuality-switchboard-lgbt-helpline-offer-their-expert-advice-35438.html"]}],"pageTitle":"Exploring your sexuality? Switchboard LGBT+ Helpline offer their expert advice - The Mix"},{"time":"3:19 PM","type":"EVENT","repeatActivityTimes":[],"details":[{"Event category":["30 sec Engagement"],"Event action":["time on page more than 30 seconds"],"Event label":["(not set)"],"Event count":["1"],"Event value":["0"]}],"name":"time on page more than 30 seconds","on":"30 sec Engagement"},{"time":"3:19 PM","type":"PAGEVIEW","repeatActivityTimes":[],"details":[{"Page title":["Exploring your sexuality? Switchboard LGBT+ Helpline offer their expert advice - The Mix"],"Page URL":["/sex-and-relationships/gender-and-sexuality/are-you-exploring-your-sexuality-switchboard-lgbt-helpline-offer-their-expert-advice-35438.html"]}],"pageTitle":"Exploring your sexuality? Switchboard LGBT+ Helpline offer their expert advice - The Mix"},{"time":"3:19 PM","type":"PAGEVIEW","repeatActivityTimes":[],"details":[{"Page title":["Exploring your sexuality? Switchboard LGBT+ Helpline offer their expert advice - The Mix"],"Page URL":["/sex-and-relationships/gender-and-sexuality/are-you-exploring-your-sexuality-switchboard-lgbt-helpline-offer-their-expert-advice-35438.html"]}],"pageTitle":"Exploring your sexuality? Switchboard LGBT+ Helpline offer their expert advice - The Mix"},{"time":"3:17 PM","type":"PAGEVIEW","repeatActivityTimes":[],"details":[{"Page title":["How to cope when a friendship ends - The Mix"],"Page URL":["/sex-and-relationships/friendship/how-to-cope-when-a-friendship-ends-37414.html"]}],"pageTitle":"How to cope when a friendship ends - The Mix"},{"time":"3:10 PM","type":"EVENT","repeatActivityTimes":[],"details":[{"Event category":["30 sec Engagement"],"Event action":["time on page more than 30 seconds"],"Event label":["(not set)"],"Event count":["1"],"Event value":["0"]}],"name":"time on page more than 30 seconds","on":"30 sec Engagement"},{"time":"3:10 PM","type":"PAGEVIEW","repeatActivityTimes":[],"details":[{"Page title":["The Mix - Essential support for under 25s"],"Page URL":["/"]}],"pageTitle":"The Mix - Essential support for under 25s"}]},{"duration":"00:29","deviceCategory":"desktop","channel":"Direct","activitySummary":{"EVENT":"1","PAGEVIEW":"1"},"activities":[{"time":"2:06 PM","type":"EVENT","repeatActivityTimes":[],"details":[{"Event category":["30 sec Engagement"],"Event action":["time on page more than 30 seconds"],"Event label":["(not set)"],"Event count":["1"],"Event value":["0"]}],"name":"time on page more than 30 seconds","on":"30 sec Engagement"},{"time":"2:05 PM","type":"PAGEVIEW","repeatActivityTimes":[],"details":[{"Page title":["The Mix - Essential support for under 25s"],"Page URL":["/"]}],"pageTitle":"The Mix - Essential support for under 25s"}]},{"duration":"00:00","deviceCategory":"desktop","channel":"Direct","activitySummary":{"PAGEVIEW":"1"},"activities":[{"time":"1:23 PM","type":"PAGEVIEW","repeatActivityTimes":[],"details":[{"Page title":["The Mix - Essential support for under 25s"],"Page URL":["/"]}],"pageTitle":"The Mix - Essential support for under 25s"}]},{"duration":"11:43","deviceCategory":"desktop","channel":"Direct","activitySummary":{"EVENT":"2","PAGEVIEW":"3"},"activities":[{"time":"8:49 AM","type":"PAGEVIEW","repeatActivityTimes":[],"details":[{"Page title":["Page Not Found - The Mix"],"Page URL":["/digital-families"]}],"pageTitle":"Page Not Found - The Mix"},{"time":"8:37 AM","type":"EVENT","repeatActivityTimes":[],"details":[{"Event category":["30 sec Engagement"],"Event action":["time on page more than 30 seconds"],"Event label":["(not set)"],"Event count":["1"],"Event value":["0"]}],"name":"time on page more than 30 seconds","on":"30 sec Engagement"},{"time":"8:37 AM","type":"EVENT","repeatActivityTimes":[],"details":[{"Event category":["30 sec Engagement"],"Event action":["time on page more than 30 seconds"],"Event label":["Forum"],"Event count":["1"],"Event value":["0"]}],"name":"time on page more than 30 seconds","on":"30 sec Engagement"},{"time":"8:37 AM","type":"PAGEVIEW","repeatActivityTimes":[],"details":[{"Page title":["What Men Need - The Mix"],"Page URL":["/your-voices/campaigns/what-men-need"]}],"pageTitle":"What Men Need - The Mix"},{"time":"8:37 AM","type":"PAGEVIEW","repeatActivityTimes":[],"details":[{"Page title":["Search — The Mix Support Community"],"Page URL":["/search?adv=&search=relationships+advice&title=&author=&cat=all&tags=&discussion_poll=1&discussion_d=1&comment_c=1&within=1+day&date="]}],"pageTitle":"Search — The Mix Support Community"}]}]},{"date":"Aug 28, 2020","hasGoal":false,"hasRevenue":false,"sessionCount":2,"sessions":[{"duration":"03:49","deviceCategory":"desktop","channel":"Direct","activitySummary":{"EVENT":"2","PAGEVIEW":"2"},"activities":[{"time":"9:34 AM","type":"EVENT","repeatActivityTimes":[],"details":[{"Event category":["30 sec Engagement"],"Event action":["time on page more than 30 seconds"],"Event label":["Forum"],"Event count":["1"],"Event value":["0"]}],"name":"time on page more than 30 seconds","on":"30 sec Engagement"},{"time":"9:34 AM","type":"PAGEVIEW","repeatActivityTimes":[],"details":[{"Page title":["Search — The Mix Support Community"],"Page URL":["/search?adv=&search=relationships+advice&title=&author=&cat=all&tags=&discussion_poll=1&discussion_d=1&comment_c=1&within=1+day&date="]}],"pageTitle":"Search — The Mix Support Community"},{"time":"9:31 AM","type":"EVENT","repeatActivityTimes":[],"details":[{"Event category":["30 sec Engagement"],"Event action":["time on page more than 30 seconds"],"Event label":["Forum"],"Event count":["1"],"Event value":["0"]}],"name":"time on page more than 30 seconds","on":"30 sec Engagement"},{"time":"9:31 AM","type":"PAGEVIEW","repeatActivityTimes":[],"details":[{"Page title":["I need girly relationship advice! Should I stay or go? — The Mix Support Community"],"Page URL":["/discussion/comment/3624570"]}],"pageTitle":"I need girly relationship advice! Should I stay or go? — The Mix Support Community"}]},{"duration":"01:03","deviceCategory":"desktop","channel":"Direct","activitySummary":{"EVENT":"2","PAGEVIEW":"2"},"activities":[{"time":"8:54 AM","type":"EVENT","repeatActivityTimes":[],"details":[{"Event category":["30 sec Engagement"],"Event action":["time on page more than 30 seconds"],"Event label":["Forum"],"Event count":["1"],"Event value":["0"]}],"name":"time on page more than 30 seconds","on":"30 sec Engagement"},{"time":"8:53 AM","type":"PAGEVIEW","repeatActivityTimes":[],"details":[{"Page title":["Search — The Mix Support Community"],"Page URL":["/search?adv=&search=relationships+advice&title=&author=&cat=all&tags=&discussion_poll=1&discussion_d=1&comment_c=1&within=1+day&date="]}],"pageTitle":"Search — The Mix Support Community"},{"time":"8:53 AM","type":"EVENT","repeatActivityTimes":[],"details":[{"Event category":["30 sec Engagement"],"Event action":["time on page more than 30 seconds"],"Event label":["Forum"],"Event count":["1"],"Event value":["0"]}],"name":"time on page more than 30 seconds","on":"30 sec Engagement"},{"time":"8:52 AM","type":"PAGEVIEW","repeatActivityTimes":[],"details":[{"Page title":["Search — The Mix Support Community"],"Page URL":["/search?adv=&search=relationships&title=&author=&cat=all&tags=&discussion_poll=1&discussion_d=1&comment_c=1&within=1+day&date="]}],"pageTitle":"Search — The Mix Support Community"}]}]}]}