{"dates":[{"date":"Feb 10, 2021","hasGoal":false,"hasRevenue":false,"sessionCount":1,"sessions":[{"duration":"01:08","deviceCategory":"mobile","channel":"Referral","activitySummary":{"EVENT":"2","PAGEVIEW":"3"},"activities":[{"time":"9:40 PM","type":"EVENT","repeatActivityTimes":[],"details":[{"Event category":["30 sec Engagement"],"Event action":["time on page more than 30 seconds"],"Event label":["(not set)"],"Event count":["1"],"Event value":["0"]}],"name":"time on page more than 30 seconds","on":"30 sec Engagement"},{"time":"9:39 PM","type":"PAGEVIEW","repeatActivityTimes":[],"details":[{"Page title":["Volunteering - The Mix"],"Page URL":["/get-involved/volunteering"]}],"pageTitle":"Volunteering - The Mix"},{"time":"9:39 PM","type":"PAGEVIEW","repeatActivityTimes":[],"details":[{"Page title":["Service Innovators Committee Member - The Mix"],"Page URL":["/get-involved/volunteering/service-shaper-steering-group-member"]}],"pageTitle":"Service Innovators Committee Member - The Mix"},{"time":"9:39 PM","type":"EVENT","repeatActivityTimes":[],"details":[{"Event category":["30 sec Engagement"],"Event action":["time on page more than 30 seconds"],"Event label":["(not set)"],"Event count":["1"],"Event value":["0"]}],"name":"time on page more than 30 seconds","on":"30 sec Engagement"},{"time":"9:39 PM","type":"PAGEVIEW","repeatActivityTimes":[],"details":[{"Page title":["Volunteering - The Mix"],"Page URL":["/get-involved/volunteering"]}],"pageTitle":"Volunteering - The Mix"}]}]}]}