{"dates":[{"date":"Apr 29, 2021","hasGoal":false,"hasRevenue":false,"sessionCount":1,"sessions":[{"duration":"00:00","deviceCategory":"desktop","channel":"Organic Search","activitySummary":{"PAGEVIEW":"1"},"activities":[{"time":"8:54 AM","type":"PAGEVIEW","repeatActivityTimes":[],"details":[{"Page title":["Speak to Our Team - The Mix"],"Page URL":["/get-support/speak-to-our-team"]}],"pageTitle":"Speak to Our Team - The Mix"}]}]},{"date":"Apr 27, 2021","hasGoal":false,"hasRevenue":false,"sessionCount":1,"sessions":[{"duration":"00:27","deviceCategory":"desktop","channel":"Organic Search","activitySummary":{"EVENT":"1","PAGEVIEW":"1"},"activities":[{"time":"9:23 AM","type":"EVENT","repeatActivityTimes":[],"details":[{"Event category":["30 sec Engagement"],"Event action":["time on page more than 30 seconds"],"Event label":["(not set)"],"Event count":["1"],"Event value":["0"]}],"name":"time on page more than 30 seconds","on":"30 sec Engagement"},{"time":"9:23 AM","type":"PAGEVIEW","repeatActivityTimes":[],"details":[{"Page title":["Speak to Our Team - The Mix"],"Page URL":["/get-support/speak-to-our-team"]}],"pageTitle":"Speak to Our Team - The Mix"}]}]},{"date":"Apr 24, 2021","hasGoal":false,"hasRevenue":false,"sessionCount":1,"sessions":[{"duration":"00:28","deviceCategory":"desktop","channel":"Organic Search","activitySummary":{"EVENT":"1","PAGEVIEW":"1"},"activities":[{"time":"11:16 AM","type":"EVENT","repeatActivityTimes":[],"details":[{"Event category":["30 sec Engagement"],"Event action":["time on page more than 30 seconds"],"Event label":["(not set)"],"Event count":["1"],"Event value":["0"]}],"name":"time on page more than 30 seconds","on":"30 sec Engagement"},{"time":"11:15 AM","type":"PAGEVIEW","repeatActivityTimes":[],"details":[{"Page title":["Speak to Our Team - The Mix"],"Page URL":["/get-support/speak-to-our-team"]}],"pageTitle":"Speak to Our Team - The Mix"}]}]},{"date":"Apr 23, 2021","hasGoal":false,"hasRevenue":false,"sessionCount":1,"sessions":[{"duration":"00:28","deviceCategory":"desktop","channel":"Organic Search","activitySummary":{"EVENT":"1","PAGEVIEW":"1"},"activities":[{"time":"9:38 AM","type":"EVENT","repeatActivityTimes":[],"details":[{"Event category":["30 sec Engagement"],"Event action":["time on page more than 30 seconds"],"Event label":["(not set)"],"Event count":["1"],"Event value":["0"]}],"name":"time on page more than 30 seconds","on":"30 sec Engagement"},{"time":"9:37 AM","type":"PAGEVIEW","repeatActivityTimes":[],"details":[{"Page title":["Speak to Our Team - The Mix"],"Page URL":["/get-support/speak-to-our-team"]}],"pageTitle":"Speak to Our Team - The Mix"}]}]},{"date":"Apr 19, 2021","hasGoal":false,"hasRevenue":false,"sessionCount":1,"sessions":[{"duration":"00:27","deviceCategory":"desktop","channel":"Organic Search","activitySummary":{"EVENT":"1","PAGEVIEW":"1"},"activities":[{"time":"8:41 PM","type":"EVENT","repeatActivityTimes":[],"details":[{"Event category":["30 sec Engagement"],"Event action":["time on page more than 30 seconds"],"Event label":["(not set)"],"Event count":["1"],"Event value":["0"]}],"name":"time on page more than 30 seconds","on":"30 sec Engagement"},{"time":"8:41 PM","type":"PAGEVIEW","repeatActivityTimes":[],"details":[{"Page title":["Speak to Our Team - The Mix"],"Page URL":["/get-support/speak-to-our-team"]}],"pageTitle":"Speak to Our Team - The Mix"}]}]},{"date":"Apr 18, 2021","hasGoal":false,"hasRevenue":false,"sessionCount":2,"sessions":[{"duration":"00:25","deviceCategory":"desktop","channel":"Organic Search","activitySummary":{"EVENT":"1","PAGEVIEW":"1"},"activities":[{"time":"2:51 PM","type":"EVENT","repeatActivityTimes":[],"details":[{"Event category":["30 sec Engagement"],"Event action":["time on page more than 30 seconds"],"Event label":["(not set)"],"Event count":["1"],"Event value":["0"]}],"name":"time on page more than 30 seconds","on":"30 sec Engagement"},{"time":"2:51 PM","type":"PAGEVIEW","repeatActivityTimes":[],"details":[{"Page title":["Speak to Our Team - The Mix"],"Page URL":["/get-support/speak-to-our-team"]}],"pageTitle":"Speak to Our Team - The Mix"}]},{"duration":"00:29","deviceCategory":"desktop","channel":"Organic Search","activitySummary":{"EVENT":"1","PAGEVIEW":"1"},"activities":[{"time":"10:38 AM","type":"EVENT","repeatActivityTimes":[],"details":[{"Event category":["30 sec Engagement"],"Event action":["time on page more than 30 seconds"],"Event label":["(not set)"],"Event count":["1"],"Event value":["0"]}],"name":"time on page more than 30 seconds","on":"30 sec Engagement"},{"time":"10:38 AM","type":"PAGEVIEW","repeatActivityTimes":[],"details":[{"Page title":["Speak to Our Team - The Mix"],"Page URL":["/get-support/speak-to-our-team"]}],"pageTitle":"Speak to Our Team - The Mix"}]}]},{"date":"Apr 17, 2021","hasGoal":false,"hasRevenue":false,"sessionCount":1,"sessions":[{"duration":"00:29","deviceCategory":"desktop","channel":"Organic Search","activitySummary":{"EVENT":"1","PAGEVIEW":"1"},"activities":[{"time":"2:57 PM","type":"EVENT","repeatActivityTimes":[],"details":[{"Event category":["30 sec Engagement"],"Event action":["time on page more than 30 seconds"],"Event label":["(not set)"],"Event count":["1"],"Event value":["0"]}],"name":"time on page more than 30 seconds","on":"30 sec Engagement"},{"time":"2:57 PM","type":"PAGEVIEW","repeatActivityTimes":[],"details":[{"Page title":["Speak to Our Team - The Mix"],"Page URL":["/get-support/speak-to-our-team"]}],"pageTitle":"Speak to Our Team - The Mix"}]}]},{"date":"Apr 15, 2021","hasGoal":false,"hasRevenue":false,"sessionCount":1,"sessions":[{"duration":"00:29","deviceCategory":"desktop","channel":"Organic Search","activitySummary":{"EVENT":"2","PAGEVIEW":"2"},"activities":[{"time":"8:12 AM","type":"EVENT","repeatActivityTimes":[],"details":[{"Event category":["30 sec Engagement"],"Event action":["time on page more than 30 seconds"],"Event label":["(not set)"],"Event count":["1"],"Event value":["0"]}],"name":"time on page more than 30 seconds","on":"30 sec Engagement"},{"time":"8:12 AM","type":"EVENT","repeatActivityTimes":[],"details":[{"Event category":["30 sec Engagement"],"Event action":["time on page more than 30 seconds"],"Event label":["(not set)"],"Event count":["1"],"Event value":["0"]}],"name":"time on page more than 30 seconds","on":"30 sec Engagement"},{"time":"8:11 AM","type":"PAGEVIEW","repeatActivityTimes":[],"details":[{"Page title":["Group chat - The Mix"],"Page URL":["/get-support/group-chat"]}],"pageTitle":"Group chat - The Mix"},{"time":"8:11 AM","type":"PAGEVIEW","repeatActivityTimes":[],"details":[{"Page title":["Speak to Our Team - The Mix"],"Page URL":["/get-support/speak-to-our-team"]}],"pageTitle":"Speak to Our Team - The Mix"}]}]},{"date":"Apr 14, 2021","hasGoal":false,"hasRevenue":false,"sessionCount":1,"sessions":[{"duration":"00:28","deviceCategory":"desktop","channel":"Organic Search","activitySummary":{"EVENT":"2","PAGEVIEW":"2"},"activities":[{"time":"7:26 AM","type":"EVENT","repeatActivityTimes":[],"details":[{"Event category":["30 sec Engagement"],"Event action":["time on page more than 30 seconds"],"Event label":["(not set)"],"Event count":["1"],"Event value":["0"]}],"name":"time on page more than 30 seconds","on":"30 sec Engagement"},{"time":"7:26 AM","type":"EVENT","repeatActivityTimes":[],"details":[{"Event category":["30 sec Engagement"],"Event action":["time on page more than 30 seconds"],"Event label":["(not set)"],"Event count":["1"],"Event value":["0"]}],"name":"time on page more than 30 seconds","on":"30 sec Engagement"},{"time":"7:26 AM","type":"PAGEVIEW","repeatActivityTimes":[],"details":[{"Page title":["Speak to Our Team - The Mix"],"Page URL":["/get-support/speak-to-our-team"]}],"pageTitle":"Speak to Our Team - The Mix"},{"time":"7:26 AM","type":"PAGEVIEW","repeatActivityTimes":[],"details":[{"Page title":["Group chat - The Mix"],"Page URL":["/get-support/group-chat"]}],"pageTitle":"Group chat - The Mix"}]}]},{"date":"Apr 12, 2021","hasGoal":false,"hasRevenue":false,"sessionCount":2,"sessions":[{"duration":"00:30","deviceCategory":"desktop","channel":"Organic Search","activitySummary":{"EVENT":"1","PAGEVIEW":"1"},"activities":[{"time":"11:19 AM","type":"EVENT","repeatActivityTimes":[],"details":[{"Event category":["30 sec Engagement"],"Event action":["time on page more than 30 seconds"],"Event label":["(not set)"],"Event count":["1"],"Event value":["0"]}],"name":"time on page more than 30 seconds","on":"30 sec Engagement"},{"time":"11:19 AM","type":"PAGEVIEW","repeatActivityTimes":[],"details":[{"Page title":["Speak to Our Team - The Mix"],"Page URL":["/get-support/speak-to-our-team"]}],"pageTitle":"Speak to Our Team - The Mix"}]},{"duration":"00:25","deviceCategory":"desktop","channel":"Organic Search","activitySummary":{"EVENT":"1","PAGEVIEW":"1"},"activities":[{"time":"8:30 AM","type":"EVENT","repeatActivityTimes":[],"details":[{"Event category":["30 sec Engagement"],"Event action":["time on page more than 30 seconds"],"Event label":["(not set)"],"Event count":["1"],"Event value":["0"]}],"name":"time on page more than 30 seconds","on":"30 sec Engagement"},{"time":"8:30 AM","type":"PAGEVIEW","repeatActivityTimes":[],"details":[{"Page title":["Group chat - The Mix"],"Page URL":["/get-support/group-chat"]}],"pageTitle":"Group chat - The Mix"}]}]},{"date":"Apr 11, 2021","hasGoal":false,"hasRevenue":false,"sessionCount":1,"sessions":[{"duration":"00:26","deviceCategory":"desktop","channel":"Organic Search","activitySummary":{"EVENT":"1","PAGEVIEW":"1"},"activities":[{"time":"9:14 AM","type":"EVENT","repeatActivityTimes":[],"details":[{"Event category":["30 sec Engagement"],"Event action":["time on page more than 30 seconds"],"Event label":["(not set)"],"Event count":["1"],"Event value":["0"]}],"name":"time on page more than 30 seconds","on":"30 sec Engagement"},{"time":"9:14 AM","type":"PAGEVIEW","repeatActivityTimes":[],"details":[{"Page title":["Group chat - The Mix"],"Page URL":["/get-support/group-chat"]}],"pageTitle":"Group chat - The Mix"}]}]},{"date":"Apr 10, 2021","hasGoal":false,"hasRevenue":false,"sessionCount":2,"sessions":[{"duration":"00:29","deviceCategory":"desktop","channel":"Organic Search","activitySummary":{"EVENT":"1","PAGEVIEW":"1"},"activities":[{"time":"4:50 PM","type":"EVENT","repeatActivityTimes":[],"details":[{"Event category":["30 sec Engagement"],"Event action":["time on page more than 30 seconds"],"Event label":["(not set)"],"Event count":["1"],"Event value":["0"]}],"name":"time on page more than 30 seconds","on":"30 sec Engagement"},{"time":"4:49 PM","type":"PAGEVIEW","repeatActivityTimes":[],"details":[{"Page title":["Speak to Our Team - The Mix"],"Page URL":["/get-support/speak-to-our-team"]}],"pageTitle":"Speak to Our Team - The Mix"}]},{"duration":"00:23","deviceCategory":"desktop","channel":"Organic Search","activitySummary":{"EVENT":"1","PAGEVIEW":"1"},"activities":[{"time":"1:04 PM","type":"EVENT","repeatActivityTimes":[],"details":[{"Event category":["30 sec Engagement"],"Event action":["time on page more than 30 seconds"],"Event label":["(not set)"],"Event count":["1"],"Event value":["0"]}],"name":"time on page more than 30 seconds","on":"30 sec Engagement"},{"time":"1:04 PM","type":"PAGEVIEW","repeatActivityTimes":[],"details":[{"Page title":["Group chat - The Mix"],"Page URL":["/get-support/group-chat"]}],"pageTitle":"Group chat - The Mix"}]}]},{"date":"Apr 9, 2021","hasGoal":false,"hasRevenue":false,"sessionCount":1,"sessions":[{"duration":"00:28","deviceCategory":"desktop","channel":"Organic Search","activitySummary":{"EVENT":"2","PAGEVIEW":"2"},"activities":[{"time":"9:46 AM","type":"EVENT","repeatActivityTimes":[],"details":[{"Event category":["30 sec Engagement"],"Event action":["time on page more than 30 seconds"],"Event label":["(not set)"],"Event count":["1"],"Event value":["0"]}],"name":"time on page more than 30 seconds","on":"30 sec Engagement"},{"time":"9:46 AM","type":"EVENT","repeatActivityTimes":[],"details":[{"Event category":["30 sec Engagement"],"Event action":["time on page more than 30 seconds"],"Event label":["(not set)"],"Event count":["1"],"Event value":["0"]}],"name":"time on page more than 30 seconds","on":"30 sec Engagement"},{"time":"9:46 AM","type":"PAGEVIEW","repeatActivityTimes":[],"details":[{"Page title":["Group chat - The Mix"],"Page URL":["/get-support/group-chat"]}],"pageTitle":"Group chat - The Mix"},{"time":"9:46 AM","type":"PAGEVIEW","repeatActivityTimes":[],"details":[{"Page title":["Speak to Our Team - The Mix"],"Page URL":["/get-support/speak-to-our-team"]}],"pageTitle":"Speak to Our Team - The Mix"}]}]},{"date":"Apr 8, 2021","hasGoal":false,"hasRevenue":false,"sessionCount":1,"sessions":[{"duration":"00:28","deviceCategory":"desktop","channel":"Organic Search","activitySummary":{"EVENT":"1","PAGEVIEW":"1"},"activities":[{"time":"8:40 AM","type":"EVENT","repeatActivityTimes":[],"details":[{"Event category":["30 sec Engagement"],"Event action":["time on page more than 30 seconds"],"Event label":["(not set)"],"Event count":["1"],"Event value":["0"]}],"name":"time on page more than 30 seconds","on":"30 sec Engagement"},{"time":"8:39 AM","type":"PAGEVIEW","repeatActivityTimes":[],"details":[{"Page title":["Group chat - The Mix"],"Page URL":["/get-support/group-chat"]}],"pageTitle":"Group chat - The Mix"}]}]},{"date":"Apr 7, 2021","hasGoal":false,"hasRevenue":false,"sessionCount":2,"sessions":[{"duration":"00:38","deviceCategory":"desktop","channel":"Organic Search","activitySummary":{"EVENT":"2","PAGEVIEW":"2"},"activities":[{"time":"9:46 PM","type":"EVENT","repeatActivityTimes":[],"details":[{"Event category":["30 sec Engagement"],"Event action":["time on page more than 30 seconds"],"Event label":["(not set)"],"Event count":["1"],"Event value":["0"]}],"name":"time on page more than 30 seconds","on":"30 sec Engagement"},{"time":"9:46 PM","type":"EVENT","repeatActivityTimes":[],"details":[{"Event category":["30 sec Engagement"],"Event action":["time on page more than 30 seconds"],"Event label":["(not set)"],"Event count":["1"],"Event value":["0"]}],"name":"time on page more than 30 seconds","on":"30 sec Engagement"},{"time":"9:46 PM","type":"PAGEVIEW","repeatActivityTimes":[],"details":[{"Page title":["Group chat - The Mix"],"Page URL":["/get-support/group-chat"]}],"pageTitle":"Group chat - The Mix"},{"time":"9:46 PM","type":"PAGEVIEW","repeatActivityTimes":[],"details":[{"Page title":["Speak to Our Team - The Mix"],"Page URL":["/get-support/speak-to-our-team"]}],"pageTitle":"Speak to Our Team - The Mix"}]},{"duration":"00:28","deviceCategory":"desktop","channel":"Organic Search","activitySummary":{"EVENT":"2","PAGEVIEW":"2"},"activities":[{"time":"9:12 AM","type":"EVENT","repeatActivityTimes":[],"details":[{"Event category":["30 sec Engagement"],"Event action":["time on page more than 30 seconds"],"Event label":["(not set)"],"Event count":["1"],"Event value":["0"]}],"name":"time on page more than 30 seconds","on":"30 sec Engagement"},{"time":"9:12 AM","type":"EVENT","repeatActivityTimes":[],"details":[{"Event category":["30 sec Engagement"],"Event action":["time on page more than 30 seconds"],"Event label":["(not set)"],"Event count":["1"],"Event value":["0"]}],"name":"time on page more than 30 seconds","on":"30 sec Engagement"},{"time":"9:12 AM","type":"PAGEVIEW","repeatActivityTimes":[],"details":[{"Page title":["Group chat - The Mix"],"Page URL":["/get-support/group-chat"]}],"pageTitle":"Group chat - The Mix"},{"time":"9:12 AM","type":"PAGEVIEW","repeatActivityTimes":[],"details":[{"Page title":["Speak to Our Team - The Mix"],"Page URL":["/get-support/speak-to-our-team"]}],"pageTitle":"Speak to Our Team - The Mix"}]}]},{"date":"Apr 6, 2021","hasGoal":false,"hasRevenue":false,"sessionCount":3,"sessions":[{"duration":"00:27","deviceCategory":"desktop","channel":"Organic Search","activitySummary":{"EVENT":"2","PAGEVIEW":"2"},"activities":[{"time":"9:26 AM","type":"EVENT","repeatActivityTimes":[],"details":[{"Event category":["30 sec Engagement"],"Event action":["time on page more than 30 seconds"],"Event label":["(not set)"],"Event count":["1"],"Event value":["0"]}],"name":"time on page more than 30 seconds","on":"30 sec Engagement"},{"time":"9:26 AM","type":"EVENT","repeatActivityTimes":[],"details":[{"Event category":["30 sec Engagement"],"Event action":["time on page more than 30 seconds"],"Event label":["(not set)"],"Event count":["1"],"Event value":["0"]}],"name":"time on page more than 30 seconds","on":"30 sec Engagement"},{"time":"9:25 AM","type":"PAGEVIEW","repeatActivityTimes":[],"details":[{"Page title":["Group chat - The Mix"],"Page URL":["/get-support/group-chat"]}],"pageTitle":"Group chat - The Mix"},{"time":"9:25 AM","type":"PAGEVIEW","repeatActivityTimes":[],"details":[{"Page title":["Speak to Our Team - The Mix"],"Page URL":["/get-support/speak-to-our-team"]}],"pageTitle":"Speak to Our Team - The Mix"}]},{"duration":"00:44","deviceCategory":"desktop","channel":"Organic Search","activitySummary":{"EVENT":"1","PAGEVIEW":"2"},"activities":[{"time":"12:14 AM","type":"EVENT","repeatActivityTimes":[],"details":[{"Event category":["30 sec Engagement"],"Event action":["time on page more than 30 seconds"],"Event label":["(not set)"],"Event count":["1"],"Event value":["0"]}],"name":"time on page more than 30 seconds","on":"30 sec Engagement"},{"time":"12:13 AM","type":"PAGEVIEW","repeatActivityTimes":[],"details":[{"Page title":["Group chat - The Mix"],"Page URL":["/get-support/group-chat"]}],"pageTitle":"Group chat - The Mix"},{"time":"12:13 AM","type":"PAGEVIEW","repeatActivityTimes":[],"details":[{"Page title":["Speak to Our Team - The Mix"],"Page URL":["/get-support/speak-to-our-team"]}],"pageTitle":"Speak to Our Team - The Mix"}]},{"duration":"11:34","deviceCategory":"desktop","channel":"Organic Search","activitySummary":{"EVENT":"9","PAGEVIEW":"21"},"activities":[{"time":"12:11 AM","type":"EVENT","repeatActivityTimes":[],"details":[{"Event category":["30 sec Engagement"],"Event action":["time on page more than 30 seconds"],"Event label":["(not set)"],"Event count":["1"],"Event value":["0"]}],"name":"time on page more than 30 seconds","on":"30 sec Engagement"},{"time":"12:11 AM","type":"PAGEVIEW","repeatActivityTimes":[],"details":[{"Page title":["Expert chat: Toilet problems - The Mix"],"Page URL":["/your-body/body-problems/expert-chat-toilet-problems-22763.html"]}],"pageTitle":"Expert chat: Toilet problems - The Mix"},{"time":"12:11 AM","type":"EVENT","repeatActivityTimes":[],"details":[{"Event category":["30 sec Engagement"],"Event action":["time on page more than 30 seconds"],"Event label":["Forum"],"Event count":["1"],"Event value":["0"]}],"name":"time on page more than 30 seconds","on":"30 sec Engagement"},{"time":"12:10 AM","type":"PAGEVIEW","repeatActivityTimes":[],"details":[{"Page title":["Home, Law & Money — The Mix Support Community"],"Page URL":["/categories/home-law-money/p3"]}],"pageTitle":"Home, Law & Money — The Mix Support Community"},{"time":"12:10 AM","type":"PAGEVIEW","repeatActivityTimes":[],"details":[{"Page title":["Search — The Mix Support Community"],"Page URL":["/search?cat=40&adv=1&search=flat+share"]}],"pageTitle":"Search — The Mix Support Community"},{"time":"12:10 AM","type":"PAGEVIEW","repeatActivityTimes":[],"details":[{"Page title":["Search — The Mix Support Community"],"Page URL":["/search?Page=p2&cat=40&adv=1&search=flat+share"]}],"pageTitle":"Search — The Mix Support Community"},{"time":"12:10 AM","type":"PAGEVIEW","repeatActivityTimes":[],"details":[{"Page title":["Search — The Mix Support Community"],"Page URL":["/search?Page=&cat=40&adv=1&search=flat+share"]}],"pageTitle":"Search — The Mix Support Community"},{"time":"12:07 AM","type":"EVENT","repeatActivityTimes":[],"details":[{"Event category":["30 sec Engagement"],"Event action":["time on page more than 30 seconds"],"Event label":["Forum"],"Event count":["1"],"Event value":["0"]}],"name":"time on page more than 30 seconds","on":"30 sec Engagement"},{"time":"12:07 AM","type":"EVENT","repeatActivityTimes":[],"details":[{"Event category":["30 sec Engagement"],"Event action":["time on page more than 30 seconds"],"Event label":["Forum"],"Event count":["1"],"Event value":["0"]}],"name":"time on page more than 30 seconds","on":"30 sec Engagement"},{"time":"12:06 AM","type":"PAGEVIEW","repeatActivityTimes":[],"details":[{"Page title":["How to choose a housemate? — The Mix Support Community"],"Page URL":["/discussion/comment/2576501"]}],"pageTitle":"How to choose a housemate? — The Mix Support Community"},{"time":"12:06 AM","type":"PAGEVIEW","repeatActivityTimes":[],"details":[{"Page title":["Search — The Mix Support Community"],"Page URL":["/search?Page=p2&cat=40&adv=1&search=flat+share"]}],"pageTitle":"Search — The Mix Support Community"},{"time":"12:06 AM","type":"PAGEVIEW","repeatActivityTimes":[],"details":[{"Page title":["Search — The Mix Support Community"],"Page URL":["/search?cat=40&adv=1&search=flat+share"]}],"pageTitle":"Search — The Mix Support Community"},{"time":"12:05 AM","type":"PAGEVIEW","repeatActivityTimes":[],"details":[{"Page title":["Home, Law & Money — The Mix Support Community"],"Page URL":["/categories/home-law-money/p3"]}],"pageTitle":"Home, Law & Money — The Mix Support Community"},{"time":"12:05 AM","type":"PAGEVIEW","repeatActivityTimes":[],"details":[{"Page title":["Housing and financial stress — The Mix Support Community"],"Page URL":["/discussion/3589212/housing-and-financial-stress"]}],"pageTitle":"Housing and financial stress — The Mix Support Community"},{"time":"12:05 AM","type":"PAGEVIEW","repeatActivityTimes":[],"details":[{"Page title":["Home, Law & Money — The Mix Support Community"],"Page URL":["/categories/home-law-money/p3"]}],"pageTitle":"Home, Law & Money — The Mix Support Community"},{"time":"12:05 AM","type":"PAGEVIEW","repeatActivityTimes":[],"details":[{"Page title":["Home, Law & Money — The Mix Support Community"],"Page URL":["/categories/home-law-money"]}],"pageTitle":"Home, Law & Money — The Mix Support Community"},{"time":"12:04 AM","type":"PAGEVIEW","repeatActivityTimes":[],"details":[{"Page title":["Home, Law & Money — The Mix Support Community"],"Page URL":["/categories/home-law-money/p2"]}],"pageTitle":"Home, Law & Money — The Mix Support Community"},{"time":"12:04 AM","type":"PAGEVIEW","repeatActivityTimes":[],"details":[{"Page title":["Awkard choice? — The Mix Support Community"],"Page URL":["/discussion/3595874/awkard-choice"]}],"pageTitle":"Awkard choice? — The Mix Support Community"},{"time":"12:04 AM","type":"PAGEVIEW","repeatActivityTimes":[],"details":[{"Page title":["Home, Law & Money — The Mix Support Community"],"Page URL":["/categories/home-law-money/p2"]}],"pageTitle":"Home, Law & Money — The Mix Support Community"},{"time":"12:04 AM","type":"PAGEVIEW","repeatActivityTimes":[],"details":[{"Page title":["Home, Law & Money — The Mix Support Community"],"Page URL":["/categories/home-law-money"]}],"pageTitle":"Home, Law & Money — The Mix Support Community"},{"time":"12:04 AM","type":"EVENT","repeatActivityTimes":[],"details":[{"Event category":["30 sec Engagement"],"Event action":["time on page more than 30 seconds"],"Event label":["(not set)"],"Event count":["1"],"Event value":["0"]}],"name":"time on page more than 30 seconds","on":"30 sec Engagement"},{"time":"12:03 AM","type":"PAGEVIEW","repeatActivityTimes":[],"details":[{"Page title":["Group chat - The Mix"],"Page URL":["/get-support/group-chat"]}],"pageTitle":"Group chat - The Mix"},{"time":"12:02 AM","type":"EVENT","repeatActivityTimes":[],"details":[{"Event category":["30 sec Engagement"],"Event action":["time on page more than 30 seconds"],"Event label":["(not set)"],"Event count":["1"],"Event value":["0"]}],"name":"time on page more than 30 seconds","on":"30 sec Engagement"},{"time":"12:01 AM","type":"EVENT","repeatActivityTimes":[],"details":[{"Event category":["30 sec Engagement"],"Event action":["time on page more than 30 seconds"],"Event label":["Forum"],"Event count":["1"],"Event value":["0"]}],"name":"time on page more than 30 seconds","on":"30 sec Engagement"},{"time":"12:01 AM","type":"PAGEVIEW","repeatActivityTimes":[],"details":[{"Page title":["Group chat - The Mix"],"Page URL":["/get-support/group-chat"]}],"pageTitle":"Group chat - The Mix"},{"time":"12:01 AM","type":"PAGEVIEW","repeatActivityTimes":[],"details":[{"Page title":["The Mix Community"],"Page URL":["/"]}],"pageTitle":"The Mix Community"},{"time":"12:01 AM","type":"EVENT","repeatActivityTimes":[],"details":[{"Event category":["30 sec Engagement"],"Event action":["time on page more than 30 seconds"],"Event label":["(not set)"],"Event count":["1"],"Event value":["0"]}],"name":"time on page more than 30 seconds","on":"30 sec Engagement"},{"time":"12:01 AM","type":"PAGEVIEW","repeatActivityTimes":[],"details":[{"Page title":["Student Life — The Mix Support Community"],"Page URL":["/categories/student"]}],"pageTitle":"Student Life — The Mix Support Community"},{"time":"12:00 AM","type":"PAGEVIEW","repeatActivityTimes":[],"details":[{"Page title":["Group chat - The Mix"],"Page URL":["/get-support/group-chat"]}],"pageTitle":"Group chat - The Mix"},{"time":"12:00 AM","type":"EVENT","repeatActivityTimes":[],"details":[{"Event category":["30 sec Engagement"],"Event action":["time on page more than 30 seconds"],"Event label":["(not set)"],"Event count":["1"],"Event value":["0"]}],"name":"time on page more than 30 seconds","on":"30 sec Engagement"}]}]},{"date":"Apr 5, 2021","hasGoal":false,"hasRevenue":false,"sessionCount":1,"sessions":[{"duration":"00:04","deviceCategory":"desktop","channel":"Organic Search","activitySummary":{"PAGEVIEW":"2"},"activities":[{"time":"11:59 PM","type":"PAGEVIEW","repeatActivityTimes":[],"details":[{"Page title":["Speak to Our Team - The Mix"],"Page URL":["/get-support/speak-to-our-team"]}],"pageTitle":"Speak to Our Team - The Mix"},{"time":"11:59 PM","type":"PAGEVIEW","repeatActivityTimes":[],"details":[{"Page title":["The Mix - Essential support for under 25s"],"Page URL":["/"]}],"pageTitle":"The Mix - Essential support for under 25s"}]}]},{"date":"Mar 31, 2021","hasGoal":false,"hasRevenue":false,"sessionCount":1,"sessions":[{"duration":"01:07","deviceCategory":"desktop","channel":"Organic Search","activitySummary":{"PAGEVIEW":"7"},"activities":[{"time":"10:50 PM","type":"PAGEVIEW","repeatActivityTimes":[],"details":[{"Page title":["Courses - The Mix"],"Page URL":["/get-involved/skill-up"]}],"pageTitle":"Courses - The Mix"},{"time":"10:49 PM","type":"PAGEVIEW","repeatActivityTimes":[],"details":[{"Page title":["Boost Your Skills - The Mix"],"Page URL":["/your-voices/boost-your-skills"]}],"pageTitle":"Boost Your Skills - The Mix"},{"time":"10:49 PM","type":"PAGEVIEW","repeatActivityTimes":[],"details":[{"Page title":["Member - The Mix"],"Page URL":["/your-voices/contributors/isabelle-eva"]}],"pageTitle":"Member - The Mix"},{"time":"10:49 PM","type":"PAGEVIEW","repeatActivityTimes":[],"details":[{"Page title":["Courses - The Mix"],"Page URL":["/get-involved/skill-up"]}],"pageTitle":"Courses - The Mix"},{"time":"10:49 PM","type":"PAGEVIEW","repeatActivityTimes":[],"details":[{"Page title":["Courses - The Mix"],"Page URL":["/get-involved/skill-up"]}],"pageTitle":"Courses - The Mix"},{"time":"10:49 PM","type":"PAGEVIEW","repeatActivityTimes":[],"details":[{"Page title":["Mental Health - The Mix"],"Page URL":["/mental-health"]}],"pageTitle":"Mental Health - The Mix"},{"time":"10:48 PM","type":"PAGEVIEW","repeatActivityTimes":[],"details":[{"Page title":["Get Support - The Mix"],"Page URL":["/get-support"]}],"pageTitle":"Get Support - The Mix"}]}]},{"date":"Mar 20, 2021","hasGoal":false,"hasRevenue":false,"sessionCount":1,"sessions":[{"duration":"02:32","deviceCategory":"desktop","channel":"Organic Search","activitySummary":{"EVENT":"1","PAGEVIEW":"6"},"activities":[{"time":"7:56 PM","type":"PAGEVIEW","repeatActivityTimes":[],"details":[{"Page title":["Courses - The Mix"],"Page URL":["/get-involved/skill-up"]}],"pageTitle":"Courses - The Mix"},{"time":"7:55 PM","type":"PAGEVIEW","repeatActivityTimes":[],"details":[{"Page title":["Recover Me - The Mix"],"Page URL":["/your-voices/campaigns/recover-me"]}],"pageTitle":"Recover Me - The Mix"},{"time":"7:55 PM","type":"PAGEVIEW","repeatActivityTimes":[],"details":[{"Page title":["Campaigns - The Mix"],"Page URL":["/your-voices/campaigns"]}],"pageTitle":"Campaigns - The Mix"},{"time":"7:55 PM","type":"PAGEVIEW","repeatActivityTimes":[],"details":[{"Page title":["Your Voices Guidelines - The Mix"],"Page URL":["/your-voices/your-voices-guidelines"]}],"pageTitle":"Your Voices Guidelines - The Mix"},{"time":"7:55 PM","type":"PAGEVIEW","repeatActivityTimes":[],"details":[{"Page title":["Submissions - The Mix"],"Page URL":["/your-voices/submissions"]}],"pageTitle":"Submissions - The Mix"},{"time":"7:54 PM","type":"EVENT","repeatActivityTimes":[],"details":[{"Event category":["30 sec Engagement"],"Event action":["time on page more than 30 seconds"],"Event label":["(not set)"],"Event count":["1"],"Event value":["0"]}],"name":"time on page more than 30 seconds","on":"30 sec Engagement"},{"time":"7:53 PM","type":"PAGEVIEW","repeatActivityTimes":[],"details":[{"Page title":["Courses - The Mix"],"Page URL":["/get-involved/skill-up"]}],"pageTitle":"Courses - The Mix"}]}]}]}