{"dates":[{"date":"Nov 16, 2020","hasGoal":false,"hasRevenue":false,"sessionCount":6,"sessions":[{"duration":"00:55","deviceCategory":"mobile","channel":"Direct","activitySummary":{"EVENT":"1","PAGEVIEW":"2"},"activities":[{"time":"10:11 PM","type":"EVENT","repeatActivityTimes":[],"details":[{"Event category":["30 sec Engagement"],"Event action":["time on page more than 30 seconds"],"Event label":["Forum"],"Event count":["1"],"Event value":["0"]}],"name":"time on page more than 30 seconds","on":"30 sec Engagement"},{"time":"10:10 PM","type":"PAGEVIEW","repeatActivityTimes":[],"details":[{"Page title":["General chit chat (OP GreenTea) - Page 556 — The Mix Support Community"],"Page URL":["/discussion/comment/3664019"]}],"pageTitle":"General chit chat (OP GreenTea) - Page 556 — The Mix Support Community"},{"time":"10:10 PM","type":"PAGEVIEW","repeatActivityTimes":[],"details":[{"Page title":["Recent Discussions — The Mix Support Community"],"Page URL":["/discussions"]}],"pageTitle":"Recent Discussions — The Mix Support Community"}]},{"duration":"20:29","deviceCategory":"mobile","channel":"Direct","activitySummary":{"EVENT":"4","PAGEVIEW":"8"},"activities":[{"time":"9:20 PM","type":"EVENT","repeatActivityTimes":[],"details":[{"Event category":["30 sec Engagement"],"Event action":["time on page more than 30 seconds"],"Event label":["Forum"],"Event count":["1"],"Event value":["0"]}],"name":"time on page more than 30 seconds","on":"30 sec Engagement"},{"time":"9:18 PM","type":"PAGEVIEW","repeatActivityTimes":[],"details":[{"Page title":["Recent Discussions — The Mix Support Community"],"Page URL":["/discussions"]}],"pageTitle":"Recent Discussions — The Mix Support Community"},{"time":"9:18 PM","type":"EVENT","repeatActivityTimes":[],"details":[{"Event category":["30 sec Engagement"],"Event action":["time on page more than 30 seconds"],"Event label":["Forum"],"Event count":["1"],"Event value":["0"]}],"name":"time on page more than 30 seconds","on":"30 sec Engagement"},{"time":"9:17 PM","type":"PAGEVIEW","repeatActivityTimes":[],"details":[{"Page title":["How I'm getting on at the moment. - Page 3 — The Mix Support Community"],"Page URL":["/discussion/3595910/how-im-getting-on-at-the-moment"]}],"pageTitle":"How I'm getting on at the moment. - Page 3 — The Mix Support Community"},{"time":"9:17 PM","type":"PAGEVIEW","repeatActivityTimes":[],"details":[{"Page title":["Recent Discussions — The Mix Support Community"],"Page URL":["/discussions"]}],"pageTitle":"Recent Discussions — The Mix Support Community"},{"time":"9:17 PM","type":"PAGEVIEW","repeatActivityTimes":[],"details":[{"Page title":["Group Chat Schedule 16th-22th November — The Mix Support Community"],"Page URL":["/discussion/3597775/group-chat-schedule-16th-22th-november"]}],"pageTitle":"Group Chat Schedule 16th-22th November — The Mix Support Community"},{"time":"9:00 PM","type":"EVENT","repeatActivityTimes":[],"details":[{"Event category":["30 sec Engagement"],"Event action":["time on page more than 30 seconds"],"Event label":["Forum"],"Event count":["1"],"Event value":["0"]}],"name":"time on page more than 30 seconds","on":"30 sec Engagement"},{"time":"9:00 PM","type":"PAGEVIEW","repeatActivityTimes":[],"details":[{"Page title":["Recent Discussions — The Mix Support Community"],"Page URL":["/discussions"]}],"pageTitle":"Recent Discussions — The Mix Support Community"},{"time":"9:00 PM","type":"PAGEVIEW","repeatActivityTimes":[],"details":[{"Page title":["The Mix Community"],"Page URL":["/"]}],"pageTitle":"The Mix Community"},{"time":"9:00 PM","type":"PAGEVIEW","repeatActivityTimes":[],"details":[{"Page title":["Sign In — The Mix Support Community"],"Page URL":["/entry/signin"]}],"pageTitle":"Sign In — The Mix Support Community"},{"time":"9:00 PM","type":"EVENT","repeatActivityTimes":[],"details":[{"Event category":["Sign In"],"Event action":["Click"],"Event label":["Community Sign In"],"Event count":["1"],"Event value":["0"]}],"name":"Click","on":"Sign In"},{"time":"9:00 PM","type":"PAGEVIEW","repeatActivityTimes":[],"details":[{"Page title":["General chit chat (OP GreenTea) - Page 556 — The Mix Support Community"],"Page URL":["/discussion/comment/3664008"]}],"pageTitle":"General chit chat (OP GreenTea) - Page 556 — The Mix Support Community"}]},{"duration":"00:47","deviceCategory":"mobile","channel":"Direct","activitySummary":{"EVENT":"1","PAGEVIEW":"1"},"activities":[{"time":"8:08 PM","type":"PAGEVIEW","repeatActivityTimes":[],"details":[{"Page title":["General chit chat (OP GreenTea) - Page 556 — The Mix Support Community"],"Page URL":["/discussion/comment/3664008"]}],"pageTitle":"General chit chat (OP GreenTea) - Page 556 — The Mix Support Community"},{"time":"8:07 PM","type":"EVENT","repeatActivityTimes":[],"details":[{"Event category":["30 sec Engagement"],"Event action":["time on page more than 30 seconds"],"Event label":["Forum"],"Event count":["1"],"Event value":["0"]}],"name":"time on page more than 30 seconds","on":"30 sec Engagement"}]},{"duration":"00:00","deviceCategory":"mobile","channel":"Direct","activitySummary":{"PAGEVIEW":"1"},"activities":[{"time":"7:36 PM","type":"PAGEVIEW","repeatActivityTimes":[],"details":[{"Page title":["General chit chat (OP GreenTea) - Page 556 — The Mix Support Community"],"Page URL":["/discussion/comment/3664008"]}],"pageTitle":"General chit chat (OP GreenTea) - Page 556 — The Mix Support Community"}]},{"duration":"17:51","deviceCategory":"mobile","channel":"Direct","activitySummary":{"EVENT":"1","PAGEVIEW":"2"},"activities":[{"time":"6:02 PM","type":"EVENT","repeatActivityTimes":[],"details":[{"Event category":["30 sec Engagement"],"Event action":["time on page more than 30 seconds"],"Event label":["Forum"],"Event count":["1"],"Event value":["0"]}],"name":"time on page more than 30 seconds","on":"30 sec Engagement"},{"time":"5:45 PM","type":"PAGEVIEW","repeatActivityTimes":[],"details":[{"Page title":["November photo challenge 📸✨ - Page 2 — The Mix Support Community"],"Page URL":["/discussion/comment/3663989"]}],"pageTitle":"November photo challenge 📸✨ - Page 2 — The Mix Support Community"},{"time":"5:45 PM","type":"PAGEVIEW","repeatActivityTimes":[],"details":[{"Page title":["Recent Discussions — The Mix Support Community"],"Page URL":["/discussions"]}],"pageTitle":"Recent Discussions — The Mix Support Community"}]},{"duration":"39:51","deviceCategory":"mobile","channel":"Direct","activitySummary":{"EVENT":"1","PAGEVIEW":"7"},"activities":[{"time":"4:51 PM","type":"EVENT","repeatActivityTimes":[],"details":[{"Event category":["30 sec Engagement"],"Event action":["time on page more than 30 seconds"],"Event label":["Forum"],"Event count":["1"],"Event value":["0"]}],"name":"time on page more than 30 seconds","on":"30 sec Engagement"},{"time":"4:29 PM","type":"PAGEVIEW","repeatActivityTimes":[],"details":[{"Page title":["Recent Discussions — The Mix Support Community"],"Page URL":["/discussions"]}],"pageTitle":"Recent Discussions — The Mix Support Community"},{"time":"4:29 PM","type":"PAGEVIEW","repeatActivityTimes":[],"details":[{"Page title":["General chit chat (OP GreenTea) - Page 556 — The Mix Support Community"],"Page URL":["/discussion/3596830/general-chit-chat-op-greentea/p556"]}],"pageTitle":"General chit chat (OP GreenTea) - Page 556 — The Mix Support Community"},{"time":"4:29 PM","type":"PAGEVIEW","repeatActivityTimes":[],"details":[{"Page title":["General chit chat (OP GreenTea) - Page 555 — The Mix Support Community"],"Page URL":["/discussion/3596830/general-chit-chat-op-greentea"]}],"pageTitle":"General chit chat (OP GreenTea) - Page 555 — The Mix Support Community"},{"time":"4:28 PM","type":"PAGEVIEW","repeatActivityTimes":[],"details":[{"Page title":["Recent Discussions — The Mix Support Community"],"Page URL":["/discussions"]}],"pageTitle":"Recent Discussions — The Mix Support Community"},{"time":"4:28 PM","type":"PAGEVIEW","repeatActivityTimes":[],"details":[{"Page title":["Anxious — The Mix Support Community"],"Page URL":["/discussion/3597774/anxious"]}],"pageTitle":"Anxious — The Mix Support Community"},{"time":"4:28 PM","type":"PAGEVIEW","repeatActivityTimes":[],"details":[{"Page title":["November photo challenge 📸✨ — The Mix Support Community"],"Page URL":["/discussion/3597663/november-photo-challenge/p1"]}],"pageTitle":"November photo challenge 📸✨ — The Mix Support Community"},{"time":"4:11 PM","type":"PAGEVIEW","repeatActivityTimes":[],"details":[{"Page title":["November photo challenge 📸✨ - Page 2 — The Mix Support Community"],"Page URL":["/discussion/comment/3663961"]}],"pageTitle":"November photo challenge 📸✨ - Page 2 — The Mix Support Community"}]}]}]}