{"dates":[{"date":"Jul 12, 2020","hasGoal":false,"hasRevenue":false,"sessionCount":1,"sessions":[{"duration":"00:00","deviceCategory":"mobile","channel":"Paid Search","activitySummary":{"PAGEVIEW":"1"},"activities":[{"time":"5:06 AM","type":"PAGEVIEW","repeatActivityTimes":[],"details":[{"Page title":["horrible intrusive thoughts that won't go away — The Mix Support Community"],"Page URL":["/discussion/145324/horrible-intrusive-thoughts-that-wont-go-away"]}],"pageTitle":"horrible intrusive thoughts that won't go away — The Mix Support Community"}]}]},{"date":"Jul 11, 2020","hasGoal":false,"hasRevenue":false,"sessionCount":1,"sessions":[{"duration":"00:00","deviceCategory":"mobile","channel":"Paid Search","activitySummary":{"PAGEVIEW":"1"},"activities":[{"time":"7:02 AM","type":"PAGEVIEW","repeatActivityTimes":[],"details":[{"Page title":["horrible intrusive thoughts that won't go away — The Mix Support Community"],"Page URL":["/discussion/145324/horrible-intrusive-thoughts-that-wont-go-away"]}],"pageTitle":"horrible intrusive thoughts that won't go away — The Mix Support Community"}]}]}]}